README.rst
setup.py
marbaloo_dogpile/__init__.py
marbaloo_dogpile.egg-info/PKG-INFO
marbaloo_dogpile.egg-info/SOURCES.txt
marbaloo_dogpile.egg-info/dependency_links.txt
marbaloo_dogpile.egg-info/requires.txt
marbaloo_dogpile.egg-info/top_level.txt
test/testcase.py