Metadata-Version: 1.1
Name: marbaloo-dogpile
Version: 0.1.0
Summary: Dogpile support for cherrypy.
Home-page: http://github.com/marbaloo/marbaloo_dogpile
Author: Mahdi Ghane.g
Author-email: UNKNOWN
License: MIT
Keywords: dogpile cherrypy marbaloo marbaloo_dogpile
Platform: UNKNOWN
Classifier: Development Status :: 3 - Alpha
Classifier: Intended Audience :: Developers
Classifier: Framework :: CherryPy
Classifier: License :: OSI Approved :: MIT License
Classifier: Operating System :: POSIX :: Linux
Classifier: Operating System :: Unix
Classifier: Programming Language :: Python :: 3 :: Only
Classifier: Topic :: Software Development :: Libraries
